README.md
setup.py
dcompy/__init__.py
dcompy/block_rx.py
dcompy/block_tx.py
dcompy/callback.py
dcompy/common.py
dcompy/config.py
dcompy/dcom.py
dcompy/log.py
dcompy/protocol.py
dcompy/rx.py
dcompy/rx_con.py
dcompy/system_error.py
dcompy/tx.py
dcompy/waitlist.py
micropython_dcompy.egg-info/PKG-INFO
micropython_dcompy.egg-info/SOURCES.txt
micropython_dcompy.egg-info/dependency_links.txt
micropython_dcompy.egg-info/top_level.txt