Metadata-Version: 2.1
Name: micropython-dcompy
Version: 1.2
Summary: dcom micropython package
Home-page: https://github.com/jdhxyy/dcom-micropython
Author: jdh99
Author-email: jdh821@163.com
License: UNKNOWN
Platform: UNKNOWN
